fidelity/__init__.py
fidelity/accounts.py
fidelity/async_client.py
fidelity/auth.py
fidelity/browser.py
fidelity/client.py
fidelity/exceptions.py
fidelity/human.py
fidelity/management.py
fidelity/models.py
fidelity/patchright_browser.py
fidelity/patchright_client.py
fidelity/selectors.py
fidelity/statements.py
fidelity/trading.py
fidelity/transfers.py
hadoku_fidelity/__init__.py
hadoku_fidelity/app.py
hadoku_fidelity/cli.py
hadoku_fidelity/service.py
hadoku_fidelity-1.1.3.dist-info/licenses/LICENSE
hadoku_fidelity-1.1.3.dist-info/METADATA
hadoku_fidelity-1.1.3.dist-info/WHEEL
hadoku_fidelity-1.1.3.dist-info/entry_points.txt
hadoku_fidelity-1.1.3.dist-info/top_level.txt
hadoku_fidelity-1.1.3.dist-info/RECORD
