Metadata-Version: 2.4
Name: hadoku-fidelity
Version: 1.1.3
Summary: Fidelity trading automation with FastAPI service for hadoku
Author-email: Hadoku <dev@hadoku.me>
License: MIT
Project-URL: Homepage, https://github.com/WolffM/hadoku-trader
Project-URL: Repository, https://github.com/WolffM/hadoku-trader
Keywords: fidelity,trading,automation,fastapi,patchright
Classifier: Development Status :: 4 - Beta
Classifier: Intended Audience :: Developers
Classifier: License :: OSI Approved :: MIT License
Classifier: Programming Language :: Python :: 3
Classifier: Programming Language :: Python :: 3.10
Classifier: Programming Language :: Python :: 3.11
Classifier: Programming Language :: Python :: 3.12
Requires-Python: >=3.10
License-File: LICENSE
Requires-Dist: playwright>=1.40.0
Requires-Dist: playwright-stealth>=1.0.0
Requires-Dist: patchright>=1.0.0
Requires-Dist: pyotp>=2.8.0
Requires-Dist: python-dotenv>=1.0.0
Requires-Dist: fastapi>=0.109.0
Requires-Dist: uvicorn>=0.27.0
Provides-Extra: dev
Requires-Dist: pytest>=7.0.0; extra == "dev"
Requires-Dist: pytest-asyncio>=0.23.0; extra == "dev"
Dynamic: license-file
